{
  "auth" : "github:hythm7",
  "authors" : [
    "Haytham Elganiny"
  ],
  "build-depends" : [ ],
  "depends" : [
    "Terminal::ANSIColor",
    "Log::Async",
    "Libarchive",
    "LibCurl"
  ],
  "description" : "A Package Manager for Raku",
  "license" : "Artistic-2.0",
  "name" : "Pakku",
  "perl" : "6.d",
  "api"  : "",
  "provides" : {
    "Pakku"                  : "lib/Pakku.rakumod",
    "Pakku::Util"            : "lib/Pakku/Util.rakumod",
    "Pakku::Log"             : "lib/Pakku/Log.rakumod",
    "Pakku::Guts"            : "lib/Pakku/Guts.rakumod",
    "Pakku::Spec"            : "lib/Pakku/Spec.rakumod",
    "Pakku::Meta"            : "lib/Pakku/Meta.rakumod",
    "Pakku::Recman"          : "lib/Pakku/Recman.rakumod",
    "Pakku::Cache"           : "lib/Pakku/Cache.rakumod",
    "Pakku::Help"            : "lib/Pakku/Help.rakumod",
    "Pakku::Repo"            : "lib/Pakku/Repo.rakumod",
    "Pakku::Test"            : "lib/Pakku/Test.rakumod",
    "Pakku::Build"           : "lib/Pakku/Build.rakumod",
    "Grammar::Pakku::Cnf"    : "lib/Grammar/Pakku/Cnf.rakumod",
    "Grammar::Pakku::Cmd"    : "lib/Grammar/Pakku/Cmd.rakumod",
    "Grammar::Pakku::Common" : "lib/Grammar/Pakku/Common.rakumod",
    "X::Pakku"               : "lib/X/Pakku.rakumod",
    "X::Pakku::Spec"         : "lib/X/Pakku/Spec.rakumod",
    "X::Pakku::Meta"         : "lib/X/Pakku/Meta.rakumod",
    "X::Pakku::Add"          : "lib/X/Pakku/Add.rakumod",
    "X::Pakku::Test"         : "lib/X/Pakku/Test.rakumod",
    "X::Pakku::Build"        : "lib/X/Pakku/Build.rakumod"
  },
  "resources" : [
    "pakku.cnf"
  ],
  "source-url" : "https://github.com/hythm7/Pakku.git",
  "tags" : [
    "spec",
    "meta",
    "module",
    "install",
    "package",
    "distribution",
    "raku"
    ],
  "test-depends" : [
  ],
  "version" : "pupa"
}
